headtype/__init__.py
headtype/_high.py
headtype/_master.py
headtype/_types.py
headtype-0.1.0.dist-info/LICENSE
headtype-0.1.0.dist-info/METADATA
headtype-0.1.0.dist-info/WHEEL
headtype-0.1.0.dist-info/top_level.txt
headtype-0.1.0.dist-info/RECORD
