Metadata-Version: 2.1
Name: headtype
Version: 0.1.0
Summary: Helps in finding types/classes associated with object
Home-page: https://github.com/sekgobela-kevin/headtype
Author: Sekgobela Kevin
Author-email: kevinnoko23@gmail.com
Project-URL: Bug Tracker, https://github.com/sekgobela-kevin/headtype/issues
Keywords: types,classes,object,find
Classifier: Intended Audience :: Developers
Classifier: Development Status :: 2 - Pre-Alpha
Classifier: Programming Language :: Python
Classifier: Programming Language :: Python :: 3
Classifier: Topic :: Software Development :: Libraries
Classifier: Topic :: Software Development :: Libraries :: Python Modules
Classifier: Topic :: Utilities
Requires-Python: >=3.6
License-File: LICENSE
